<process-definition name="parallel-review">
	<start-state>
    <task swimlane="initiator" />
		<transition to="choose participants node" />
	</start-state>
	<task-node name="choose participants node">
		<task name="choose participant" swinlane="initiator"/>
		<transition name="to fork each participant" to="fork each participant" />
	</task-node>
	<node name="fork each participant">
    <action class="org.nuxeo.ecm.platform.jbpm.core.node.ForeachFork">
      <var>participant</var>
      <list>participants</list>
    </action>
    <transition to="validate node" />
  </node>
	<task-node name="validate node">
		<task name="validate">
			<assignement actor-id="participant.actorId" />
		</task>
		<transition to="participants join"/>
	</task-node>
	<join name="participants join">
		<transition to="end" />
	</join>
	<end-state name="end"/>
</process-definition>
